zzmtrgd
