Metadata-Version: 2.1
Name: zzmtrgd
Version: 0.9.3.1
Summary: Metodo MTR
Author-email: ramosjack066@gmail.com
License: MIT
Keywords: testing,example
